ChangeLog
README.txt
release_howto.rst
setup.cfg
setup.py
tgMochiKit.egg-info/PKG-INFO
tgMochiKit.egg-info/SOURCES.txt
tgMochiKit.egg-info/dependency_links.txt
tgMochiKit.egg-info/entry_points.txt
tgMochiKit.egg-info/not-zip-safe
tgMochiKit.egg-info/top_level.txt
tgmochikit/__init__.py
tgmochikit/base.py
tgmochikit/release.py
tgmochikit/static/javascript/1.3.1/packed/MochiKit/MochiKit.js
tgmochikit/static/javascript/1.3.1/packed/MochiKit/__package__.js
tgmochikit/static/javascript/1.3.1/unpacked/Async.js
tgmochikit/static/javascript/1.3.1/unpacked/Base.js
tgmochikit/static/javascript/1.3.1/unpacked/Color.js
tgmochikit/static/javascript/1.3.1/unpacked/DOM.js
tgmochikit/static/javascript/1.3.1/unpacked/DateTime.js
tgmochikit/static/javascript/1.3.1/unpacked/Format.js
tgmochikit/static/javascript/1.3.1/unpacked/Iter.js
tgmochikit/static/javascript/1.3.1/unpacked/Logging.js
tgmochikit/static/javascript/1.3.1/unpacked/LoggingPane.js
tgmochikit/static/javascript/1.3.1/unpacked/MochiKit.js
tgmochikit/static/javascript/1.3.1/unpacked/MockDOM.js
tgmochikit/static/javascript/1.3.1/unpacked/Signal.js
tgmochikit/static/javascript/1.3.1/unpacked/Test.js
tgmochikit/static/javascript/1.3.1/unpacked/Visual.js
tgmochikit/static/javascript/1.3.1/unpacked/__package__.js
tgmochikit/static/javascript/1.4.1/packed/MochiKit/MochiKit.js
tgmochikit/static/javascript/1.4.1/packed/MochiKit/__package__.js
tgmochikit/static/javascript/1.4.1/unpacked/Async.js
tgmochikit/static/javascript/1.4.1/unpacked/Base.js
tgmochikit/static/javascript/1.4.1/unpacked/Color.js
tgmochikit/static/javascript/1.4.1/unpacked/DOM.js
tgmochikit/static/javascript/1.4.1/unpacked/DateTime.js
tgmochikit/static/javascript/1.4.1/unpacked/DragAndDrop.js
tgmochikit/static/javascript/1.4.1/unpacked/Format.js
tgmochikit/static/javascript/1.4.1/unpacked/Iter.js
tgmochikit/static/javascript/1.4.1/unpacked/Logging.js
tgmochikit/static/javascript/1.4.1/unpacked/LoggingPane.js
tgmochikit/static/javascript/1.4.1/unpacked/MochiKit.js
tgmochikit/static/javascript/1.4.1/unpacked/MockDOM.js
tgmochikit/static/javascript/1.4.1/unpacked/Position.js
tgmochikit/static/javascript/1.4.1/unpacked/Selector.js
