Metadata-Version: 1.0
Name: tgMochiKit
Version: 1.4.2beta1
Summary: MochiKit packaged as TurboGears widgets.
Home-page: http://docs.turbogears.org/tgMochiKit
Author: Diez B. Roggisch
Author-email: deets@web.de
License: MIT
Download-URL: http://pypi.python.org/pypi/tgMochiKit
Keywords: turbogears.widgets
Platform: UNKNOWN
Classifier: Development Status :: 3 - Alpha
Classifier: Operating System :: OS Independent
Classifier: Programming Language :: Python
Classifier: Topic :: Software Development :: Libraries :: Python Modules
Classifier: Framework :: TurboGears
Classifier: Framework :: TurboGears :: Widgets
